Metadata-Version: 2.1
Name: a_pandas_ex_adb_settings_to_df
Version: 0.10
Summary: # Parses all Android config files (json/db/xml) in the /data/ folder and returns an easy-to-handle DataFrame
Home-page: https://github.com/hansalemaos/a_pandas_ex_adb_settings_to_df
Author: Johannes Fischer
Author-email: <aulasparticularesdealemaosp@gmail.com>
License: MIT
Keywords: settings,adb,pandas,DataFrame,content,android,providers
Classifier: Development Status :: 4 - Beta
Classifier: Programming Language :: Python :: 3 :: Only
Classifier: Programming Language :: Python :: 3.9
Classifier: Topic :: Scientific/Engineering :: Visualization
Classifier: Topic :: Software Development :: Libraries :: Python Modules
Classifier: Topic :: Text Editors :: Text Processing
Classifier: Topic :: Text Processing :: General
Classifier: Topic :: Text Processing :: Indexing
Classifier: Topic :: Text Processing :: Filters
Classifier: Topic :: Utilities
License-File: LICENSE.rst
